IBTrading.py
IBTrading-1.0.3.dist-info/METADATA
IBTrading-1.0.3.dist-info/WHEEL
IBTrading-1.0.3.dist-info/top_level.txt
IBTrading-1.0.3.dist-info/RECORD
