Metadata-Version: 2.1
Name: IBTrading
Version: 1.0.3
Summary: MT5 automation
Home-page: https://github.com/IB-Solution/IBTrading
Author: Hamidou Alix
Author-email: alix.hamidou@gmail.com
Classifier: Programming Language :: Python :: 3
Classifier: Intended Audience :: Developers
Classifier: Intended Audience :: Financial and Insurance Industry
Classifier: License :: OSI Approved :: Apache Software License
Classifier: Operating System :: Microsoft :: Windows
Classifier: Operating System :: Unix
Requires-Dist: MetaTrader5 (~=5.0.37)
Provides-Extra: dev
Requires-Dist: pytest (>=3.7) ; extra == 'dev'
